LICENSE
MANIFEST.in
README.md
requirements.txt
setup.py
gcdt_gru/__init__.py
gcdt_gru/app.py
gcdt_gru.egg-info/PKG-INFO
gcdt_gru.egg-info/SOURCES.txt
gcdt_gru.egg-info/dependency_links.txt
gcdt_gru.egg-info/entry_points.txt
gcdt_gru.egg-info/top_level.txt