Metadata-Version: 1.1
Name: gcdt-gru
Version: 0.6.1
Summary: Scaffolding addon for gcdt lambda
Home-page: UNKNOWN
Author: glomex OPS Team
Author-email: mark.fink@glomex.com
License: MIT
Platform: UNKNOWN
Classifier: Development Status :: 3 - Alpha
Classifier: Intended Audience :: Developers
Classifier: Programming Language :: Python :: 2.7
